peptide_forest/__init__.py
peptide_forest/knowledge_base.py
peptide_forest/peptide_forest.py
peptide_forest/prep.py
peptide_forest/regressor_model.py
peptide_forest/results.py
peptide_forest/tools.py
peptide_forest/training.py
peptide_forest/version.txt
peptide_forest-3.1.1.dist-info/licenses/LICENSE
tests/__init__.py
tests/conftest.py
tests/test_prep.py
tests/test_regressor_model.py
tests/test_results.py
tests/test_training.py
tests/_data/mascot_dat2csv_1_0_0.csv
tests/_data/omssa_2_1_9.csv
tests/_data/path_dict_medium.json
tests/_data/path_dict_medium_with_mapping.json
tests/_data/quant_data/quant_data.csv
tests/_data/raw_data/data_without_mscores.csv
peptide_forest-3.1.1.dist-info/METADATA
peptide_forest-3.1.1.dist-info/WHEEL
peptide_forest-3.1.1.dist-info/top_level.txt
peptide_forest-3.1.1.dist-info/RECORD
