Metadata-Version: 2.4
Name: peptide_forest
Version: 3.1.1
Summary: Integrate multiple search engines
Home-page: https://github.com/peptideforest/peptideForest
Author: T. Ranff, M. Dennison, J. Bédorf, S. Schulze, N. Zinn, M. Bantscheff, J.J.R.M. van Heugten, C. Fufezan
Author-email: christian@fufezan.net
License: MIT
Classifier: Development Status :: 4 - Beta
Classifier: Environment :: Console
Classifier: Intended Audience :: Education
Classifier: Intended Audience :: Science/Research
Classifier: Intended Audience :: Developers
Classifier: License :: OSI Approved :: Apache Software License
Classifier: Operating System :: MacOS :: MacOS X
Classifier: Operating System :: Microsoft :: Windows
Classifier: Operating System :: POSIX
Classifier: Operating System :: POSIX :: SunOS/Solaris
Classifier: Operating System :: Unix
Classifier: Programming Language :: Python :: 3.8
Classifier: Programming Language :: Python :: 3.9
Classifier: Programming Language :: Python :: 3.10
Classifier: Programming Language :: Python :: 3.11
Classifier: Topic :: Scientific/Engineering :: Bio-Informatics
Classifier: Topic :: Scientific/Engineering :: Chemistry
Classifier: Topic :: Scientific/Engineering :: Medical Science Apps.
License-File: LICENSE
Requires-Dist: numpy<1.27.0,>=1.21.5
Requires-Dist: pandas<2.3.0,>=1.3.5
Requires-Dist: uparma<1.1.0,>=0.9.14
Requires-Dist: loguru<0.8.0,>=0.5.3
Requires-Dist: scikit-learn<1.5,>=1.2
Requires-Dist: tqdm
Requires-Dist: pytest<8.2.0,>=6.2.5
Requires-Dist: xgboost<2.1.0,>=1.5.0
Provides-Extra: docs
Requires-Dist: sphinx; extra == "docs"
Requires-Dist: sphinx-rtd-theme; extra == "docs"
Dynamic: license-file
